setup.py
programmable_mock_client/__init__.py
programmable_mock_client.egg-info/PKG-INFO
programmable_mock_client.egg-info/SOURCES.txt
programmable_mock_client.egg-info/dependency_links.txt
programmable_mock_client.egg-info/not-zip-safe
programmable_mock_client.egg-info/requires.txt
programmable_mock_client.egg-info/top_level.txt