Metadata-Version: 1.0
Name: programmable-mock-client
Version: 1.0
Summary: Programmable Mock
Home-page: UNKNOWN
Author: Dmytro Drachov
Author-email: dmytro.drachov@gmail.com
License: none
Platform: UNKNOWN
